[
	{
		ingredientPattern: "CI",
		ingredients: {
			"C": { type: "item", code: "game:saw-*", isTool: true},
			"I": { type: "block", code: "game:clutter", attributes:{type:"barricade1"}}
		},
		width: 1,
		height: 2,
		recipeGroup: 2,
		output: { type: "block", code: "game:log-placed-aged-ud", quantity: 5 }
	},
	{
		ingredientPattern: "CI",
		ingredients: {
			"C": { type: "item", code: "game:saw-*", isTool: true},
			"I": { type: "block", code: "game:clutter", attributes:{type:"barricade2"}}
		},
		width: 1,
		height: 2,
		recipeGroup: 2,
		output: { type: "block", code: "game:log-placed-aged-ud", quantity: 6 }
	},
	{
		ingredientPattern: "CI",
		ingredients: {
			"C": { type: "item", code: "game:chisel-*", isTool: true},
			"I": { type: "block", code: "game:clutter", attributes:{type:"barricade3"}}
		},
		width: 1,
		height: 2,
		recipeGroup: 2,
		output: { type: "item", code: "game:metalbit-iron", quantity: 40 }
	},
	{
		ingredientPattern: "CI",
		ingredients: {
			"C": { type: "item", code: "game:saw-*", isTool: true},
			"I": { type: "block", code: "game:clutter", attributes:{type:"barricade5"}}
		},
		width: 1,
		height: 2,
		recipeGroup: 2,
		output: { type: "block", code: "game:log-placed-aged-ud", quantity: 5 }
	},
	{
		ingredientPattern: "CI",
		ingredients: {
			"C": { type: "item", code: "game:saw-*", isTool: true},
			"I": { type: "block", code: "game:clutter", attributes:{type:"barricade6"}}
		},
		width: 1,
		height: 2,
		recipeGroup: 2,
		output: { type: "block", code: "game:log-placed-aged-ud", quantity: 5 }
	},
]
